{"name":"Gat","tagline":"An HTTP caching server","body":"# Gat [![Build Status](https://travis-ci.org/vishr/gat.png?branch=master)](https://travis-ci.org/vishr/gat)\r\nAn HTTP caching server\r\n\r\n## Features\r\n* Supports http and https protocols\r\n* Configurable limit for the cache - coming soon!\r\n* Automatically deletes the resouce not found on the remote host\r\n* Automatically reclaims the disk space based on LRU - coming soon!\r\n* Saves bandwidth and time\r\n\r\n## Installation\r\n```sh\r\n  $ npm i gat -g\r\n```\r\n\r\n## Usage\r\n\r\n### Standalone\r\n```sh\r\n  $ gat -h\r\n\r\n    Usage: gat [options] [command]\r\n\r\n    Commands:\r\n\r\n      config                 show config\r\n      start                  start gat\r\n      stop                   stop gat\r\n      restart                restart gat\r\n      empty                  empty cache\r\n      *                      unknown command\r\n\r\n    Options:\r\n\r\n      -h, --help     output usage information\r\n      -V, --version  output the version number\r\n      -e, --edit     edit config\r\n\r\n  $ gat start\r\n  info: starting gat on port 1947\r\n\r\n  $ gat config      # show config\r\n\r\n  $ gat -e config   # edit config\r\n\r\n```\r\n**Request**\r\n```sh\r\n  curl -O \"http://localhost:1947/?protocol=https&hostname=dl.dropbox.com&resource=/u/11522638/node.png\"\r\n```\r\n**Response**\r\n```sh\r\n  HTTP/1.1 200 OK\r\n  server: Gat/0.0.9\r\n  date: Sun, 10 Mar 2013 17:31:27 GMT\r\n  content-type: image/png\r\n  content-length: 817701\r\n  connection: keep-alive\r\n  x-robots-tag: noindex,nofollow\r\n  accept-ranges: bytes\r\n  x-server-response-time: 523\r\n  x-dropbox-request-id: 7914ee643fdfb67b\r\n  pragma: public\r\n  cache-control: max-age=0\r\n```\r\n\r\n### As a node module\r\n```js\r\n  var os = require(\"os\");\r\n  var fs = require(\"fs\");\r\n  var path = require(\"path\");\r\n  var Gat = require(\"../gat\").Gat;\r\n\r\n  var FILE = \"walle.png\";\r\n  var FILE_PATH = path.join(os.tmpDir(), FILE);\r\n\r\n  Gat.setConfig({\r\n    port: 3737\r\n  });\r\n\r\n  var gat = new Gat(\"https\", \"dl.dropbox.com\");\r\n  gat.get(\"/u/11522638/\" + FILE, null, function(err, stream) {\r\n    if (err) {\r\n      return console.error(err);\r\n    }\r\n    stream.pipe(fs.createWriteStream(FILE_PATH));\r\n    stream.on(\"close\", function() {\r\n      console.info(\"File saved: \" + FILE_PATH);\r\n    });\r\n  });\r\n```\r\n","google":"UA-27473452-1","note":"Don't delete this file! It's used internally to help with page regeneration."}